{
    "version": 1,
    "license": null,
    "copyright": null,
    "size": {
        "x": 32,
        "y": 32
    },
    "states": [
        {
            "name": "Icon"
        },
        {
            "name": "Barbed"
        },
        {
            "name": "Full"
        },
        {
            "name": "barbed_wire",
            "directions": 4
        },
        {
            "name": "Broken"
        },
        {
            "name": "barbed_wire_broken",
            "directions": 4
        }
    ]
}